gerrit_hooks/__init__.py
gerrit_hooks/actions.py
gerrit_hooks/containers.py
gerrit_hooks/hook.py
gerrit_hooks/parsers.py
gerrit_hooks/utils.py
gerrit_hooks/containers/__init__.py
gerrit_hooks/containers/base.py
gerrit_hooks/containers/flag_configs.py
gerrit_hooks/containers/flags.py
gerrit_hooks/containers/hooks.py
gerrit_hooks-2.0.0.dist-info/LICENSE
gerrit_hooks-2.0.0.dist-info/METADATA
gerrit_hooks-2.0.0.dist-info/WHEEL
gerrit_hooks-2.0.0.dist-info/top_level.txt
gerrit_hooks-2.0.0.dist-info/RECORD
