Metadata-Version: 2.1
Name: gerrit-hooks
Version: 2.0.0
Summary: Utility for writing Gerrit Hooks in python
Home-page: UNKNOWN
Author: Nils Diefenbach
Author-email: nlsdfnbch.foss@kolabnow.com
License: UNKNOWN
Platform: UNKNOWN
Classifier: Development Status :: 5 - Production/Stable
Classifier: Intended Audience :: Developers
Classifier: Programming Language :: Python :: 3.5
Classifier: Programming Language :: Python :: 3.6
Classifier: Programming Language :: Python :: 3.7
Classifier: Topic :: Software Development
Classifier: Topic :: Software Development :: Code Generators
Classifier: Topic :: Software Development :: Build Tools
Classifier: Topic :: Software Development :: Version Control
Classifier: License :: OSI Approved :: MIT License
